notiontomd/__init__.py
notiontomd/notion2md.py
notiontomd-0.2.0.dist-info/LICENSE
notiontomd-0.2.0.dist-info/METADATA
notiontomd-0.2.0.dist-info/WHEEL
notiontomd-0.2.0.dist-info/top_level.txt
notiontomd-0.2.0.dist-info/RECORD
