Metadata-Version: 2.1
Name: notiontomd
Version: 0.2.0
Summary: convert notion page content to markdown
Home-page: https://github.com/akkuman/notiontomd
Author: Akkuman
Author-email: akkumans@qq.com
Classifier: Programming Language :: Python :: 3
Classifier: License :: OSI Approved :: MIT License
Classifier: Operating System :: OS Independent
License-File: LICENSE
Requires-Dist: notion-client
Requires-Dist: markdown
